JiqiZhixin2019GaofenJiaochengYuyanFix1/README.md
JiqiZhixin2019GaofenJiaochengYuyanFix1/__init__.py
JiqiZhixin2019GaofenJiaochengYuyanFix1/__main__.py
JiqiZhixin2019GaofenJiaochengYuyanFix1/file.epub
JiqiZhixin2019GaofenJiaochengYuyanFix1/index.html
JiqiZhixin2019GaofenJiaochengYuyanFix1/css/__init__.py
JiqiZhixin2019GaofenJiaochengYuyanFix1/css/annotations.css
JiqiZhixin2019GaofenJiaochengYuyanFix1/css/main.css
JiqiZhixin2019GaofenJiaochengYuyanFix1/css/normalize.css
JiqiZhixin2019GaofenJiaochengYuyanFix1/css/popup.css
JiqiZhixin2019GaofenJiaochengYuyanFix1/font/__init__.py
JiqiZhixin2019GaofenJiaochengYuyanFix1/font/fontello.eot
JiqiZhixin2019GaofenJiaochengYuyanFix1/font/fontello.svg
JiqiZhixin2019GaofenJiaochengYuyanFix1/font/fontello.ttf
JiqiZhixin2019GaofenJiaochengYuyanFix1/font/fontello.woff
JiqiZhixin2019GaofenJiaochengYuyanFix1/img/__init__.py
JiqiZhixin2019GaofenJiaochengYuyanFix1/img/annotator-glyph-sprite.png
JiqiZhixin2019GaofenJiaochengYuyanFix1/img/annotator-icon-sprite.png
JiqiZhixin2019GaofenJiaochengYuyanFix1/img/apple-touch-icon.png
JiqiZhixin2019GaofenJiaochengYuyanFix1/img/cancelfullscreen.png
JiqiZhixin2019GaofenJiaochengYuyanFix1/img/close.png
JiqiZhixin2019GaofenJiaochengYuyanFix1/img/fullscreen.png
JiqiZhixin2019GaofenJiaochengYuyanFix1/img/loader.gif
JiqiZhixin2019GaofenJiaochengYuyanFix1/img/menu-icon.png
JiqiZhixin2019GaofenJiaochengYuyanFix1/img/save.png
JiqiZhixin2019GaofenJiaochengYuyanFix1/img/saved.png
JiqiZhixin2019GaofenJiaochengYuyanFix1/img/settings-s.png
JiqiZhixin2019GaofenJiaochengYuyanFix1/img/settings.png
JiqiZhixin2019GaofenJiaochengYuyanFix1/img/star.png
JiqiZhixin2019GaofenJiaochengYuyanFix1/js/__init__.py
JiqiZhixin2019GaofenJiaochengYuyanFix1/js/epub.js
JiqiZhixin2019GaofenJiaochengYuyanFix1/js/epub.min.js
JiqiZhixin2019GaofenJiaochengYuyanFix1/js/epub.min.map
JiqiZhixin2019GaofenJiaochengYuyanFix1/js/hooks.min.js
JiqiZhixin2019GaofenJiaochengYuyanFix1/js/hooks.min.map
jiqi_zhixin_2019_gaofen_jiaocheng_yuyan_fix1-2025.3.24.0.dist-info/METADATA
jiqi_zhixin_2019_gaofen_jiaocheng_yuyan_fix1-2025.3.24.0.dist-info/WHEEL
jiqi_zhixin_2019_gaofen_jiaocheng_yuyan_fix1-2025.3.24.0.dist-info/entry_points.txt
jiqi_zhixin_2019_gaofen_jiaocheng_yuyan_fix1-2025.3.24.0.dist-info/top_level.txt
jiqi_zhixin_2019_gaofen_jiaocheng_yuyan_fix1-2025.3.24.0.dist-info/RECORD
